adafruit_sths34pf80.py
adafruit_circuitpython_sths34pf80-1.0.0.dist-info/licenses/LICENSE
adafruit_circuitpython_sths34pf80-1.0.0.dist-info/METADATA
adafruit_circuitpython_sths34pf80-1.0.0.dist-info/WHEEL
adafruit_circuitpython_sths34pf80-1.0.0.dist-info/top_level.txt
adafruit_circuitpython_sths34pf80-1.0.0.dist-info/RECORD
