Metadata-Version: 2.4
Name: adafruit-circuitpython-sths34pf80
Version: 1.0.0
Summary: CircuitPython driver for the Adafruit STHS34PF80 IR Presence / Motion Sensor - STEMMA QT / Qwiic
Author-email: Adafruit Industries <circuitpython@adafruit.com>
License: MIT
Project-URL: Homepage, https://github.com/adafruit/Adafruit_CircuitPython_STHS34PF80
Keywords: adafruit,blinka,circuitpython,micropython,sths34pf80,presence,,motion,,IR
Classifier: Intended Audience :: Developers
Classifier: Topic :: Software Development :: Libraries
Classifier: Topic :: Software Development :: Embedded Systems
Classifier: Topic :: System :: Hardware
Classifier: License :: OSI Approved :: MIT License
Classifier: Programming Language :: Python :: 3
License-File: LICENSE
Requires-Dist: Adafruit-Blinka
Requires-Dist: adafruit-circuitpython-busdevice
Requires-Dist: adafruit-circuitpython-register
Provides-Extra: optional
Dynamic: license-file
